[1,["83S+iKNM1FOZ+O03Drr4wR","d46YdJjstJ25+kqV1jFH9E"],0,[["sp.SkeletonData",["_name","_atlasText","textureNames","_skeletonJson","textures"],-1,3]],[[0,0,1,2,3,4,5]],[[0,"zhongjiangdikuang","\nzhongjiangdikuang.png\nsize: 2048,2048\nformat: RGBA8888\nfilter: Linear,Linear\nrepeat: none\nps_vfx_b_add_00\n  rotate: false\n  xy: 911, 1129\n  size: 441, 431\n  orig: 441, 431\n  offset: 0, 0\n  index: -1\nps_vfx_b_add_01\n  rotate: false\n  xy: 1366, 1586\n  size: 441, 431\n  orig: 441, 431\n  offset: 0, 0\n  index: -1\nps_vfx_b_add_02\n  rotate: false\n  xy: 456, 215\n  size: 441, 431\n  orig: 441, 431\n  offset: 0, 0\n  index: -1\nps_vfx_b_add_03\n  rotate: false\n  xy: 911, 697\n  size: 441, 431\n  orig: 441, 431\n  offset: 0, 0\n  index: -1\nps_vfx_b_add_04\n  rotate: false\n  xy: 911, 265\n  size: 441, 431\n  orig: 441, 431\n  offset: 0, 0\n  index: -1\nps_vfx_b_add_05\n  rotate: false\n  xy: 1366, 1154\n  size: 441, 431\n  orig: 441, 431\n  offset: 0, 0\n  index: -1\nps_vfx_b_add_06\n  rotate: false\n  xy: 1353, 722\n  size: 441, 431\n  orig: 441, 431\n  offset: 0, 0\n  index: -1\nps_vfx_b_add_07\n  rotate: false\n  xy: 1353, 290\n  size: 441, 431\n  orig: 441, 431\n  offset: 0, 0\n  index: -1\nps_vfx_c_add_00\n  rotate: false\n  xy: 1, 1561\n  size: 454, 456\n  orig: 454, 456\n  offset: 0, 0\n  index: -1\nps_vfx_c_add_01\n  rotate: false\n  xy: 1, 1104\n  size: 454, 456\n  orig: 454, 456\n  offset: 0, 0\n  index: -1\nps_vfx_c_add_02\n  rotate: false\n  xy: 456, 1561\n  size: 454, 456\n  orig: 454, 456\n  offset: 0, 0\n  index: -1\nps_vfx_c_add_03\n  rotate: false\n  xy: 1, 647\n  size: 454, 456\n  orig: 454, 456\n  offset: 0, 0\n  index: -1\nps_vfx_c_add_04\n  rotate: false\n  xy: 456, 1104\n  size: 454, 456\n  orig: 454, 456\n  offset: 0, 0\n  index: -1\nps_vfx_c_add_05\n  rotate: false\n  xy: 911, 1561\n  size: 454, 456\n  orig: 454, 456\n  offset: 0, 0\n  index: -1\nps_vfx_c_add_06\n  rotate: false\n  xy: 1, 190\n  size: 454, 456\n  orig: 454, 456\n  offset: 0, 0\n  index: -1\nps_vfx_c_add_07\n  rotate: false\n  xy: 456, 647\n  size: 454, 456\n  orig: 454, 456\n  offset: 0, 0\n  index: -1\nps_vfx_d_add\n  rotate: true\n  xy: 1165, 1\n  size: 263, 249\n  orig: 263, 249\n  offset: 0, 0\n  index: -1\nps_vfx_f_add\n  rotate: false\n  xy: 898, 10\n  size: 266, 254\n  orig: 266, 254\n  offset: 0, 0\n  index: -1\n\nzhongjiangdikuang2.png\nsize: 2048,2048\nformat: RGBA8888\nfilter: Linear,Linear\nrepeat: none\nps_vfx_b_add_08\n  rotate: false\n  xy: 1, 1297\n  size: 441, 431\n  orig: 441, 431\n  offset: 0, 0\n  index: -1\nps_vfx_b_add_09\n  rotate: false\n  xy: 1, 865\n  size: 441, 431\n  orig: 441, 431\n  offset: 0, 0\n  index: -1\nps_vfx_b_add_10\n  rotate: false\n  xy: 443, 1297\n  size: 441, 431\n  orig: 441, 431\n  offset: 0, 0\n  index: -1\nps_vfx_b_add_11\n  rotate: false\n  xy: 1, 433\n  size: 441, 431\n  orig: 441, 431\n  offset: 0, 0\n  index: -1\nps_vfx_b_add_12\n  rotate: false\n  xy: 443, 865\n  size: 441, 431\n  orig: 441, 431\n  offset: 0, 0\n  index: -1\nps_vfx_b_add_13\n  rotate: false\n  xy: 885, 1297\n  size: 441, 431\n  orig: 441, 431\n  offset: 0, 0\n  index: -1\nps_vfx_b_add_14\n  rotate: false\n  xy: 1, 1\n  size: 441, 431\n  orig: 441, 431\n  offset: 0, 0\n  index: -1\nps_vfx_b_add_15\n  rotate: false\n  xy: 443, 433\n  size: 441, 431\n  orig: 441, 431\n  offset: 0, 0\n  index: -1\nps_vfx_b_add_16\n  rotate: false\n  xy: 885, 865\n  size: 441, 431\n  orig: 441, 431\n  offset: 0, 0\n  index: -1\nps_vfx_b_add_17\n  rotate: false\n  xy: 1327, 1297\n  size: 441, 431\n  orig: 441, 431\n  offset: 0, 0\n  index: -1\nps_vfx_b_add_18\n  rotate: false\n  xy: 443, 1\n  size: 441, 431\n  orig: 441, 431\n  offset: 0, 0\n  index: -1\nps_vfx_b_add_19\n  rotate: false\n  xy: 885, 433\n  size: 441, 431\n  orig: 441, 431\n  offset: 0, 0\n  index: -1\nps_vfx_b_add_20\n  rotate: false\n  xy: 1327, 865\n  size: 441, 431\n  orig: 441, 431\n  offset: 0, 0\n  index: -1\nps_vfx_e_add\n  rotate: false\n  xy: 885, 83\n  size: 382, 349\n  orig: 382, 349\n  offset: 0, 0\n  index: -1\n",["zhongjiangdikuang.png","zhongjiangdikuang2.png"],{"skeleton":{"hash":"J3s9E1RkbJLcHW2abwyx9gkn2Ts","spine":"3.6.53","width":382,"height":349,"images":""},"bones":[{"name":"root"},{"name":"dikuang","parent":"root"},{"name":"dikuang2","parent":"root"},{"name":"dikuang3","parent":"root"},{"name":"fg","parent":"root"},{"name":"fg2","parent":"root"}],"slots":[{"name":"dikuang","bone":"dikuang","attachment":"ps_vfx_f_add","blend":"additive"},{"name":"dikuang2","bone":"dikuang2","attachment":"ps_vfx_d_add","blend":"additive"},{"name":"dikuang3","bone":"dikuang3","attachment":"ps_vfx_e_add","blend":"additive"},{"name":"fg2","bone":"fg2","blend":"additive"},{"name":"fg","bone":"fg","blend":"additive"}],"skins":{"default":{"dikuang":{"ps_vfx_f_add":{"width":266,"height":254}},"dikuang2":{"ps_vfx_d_add":{"width":263,"height":249}},"dikuang3":{"ps_vfx_e_add":{"width":382,"height":349}},"fg":{"ps_vfx_b_add_00":{"width":441,"height":431},"ps_vfx_b_add_01":{"width":441,"height":431},"ps_vfx_b_add_02":{"width":441,"height":431},"ps_vfx_b_add_03":{"width":441,"height":431},"ps_vfx_b_add_04":{"width":441,"height":431},"ps_vfx_b_add_05":{"width":441,"height":431},"ps_vfx_b_add_06":{"width":441,"height":431},"ps_vfx_b_add_07":{"width":441,"height":431},"ps_vfx_b_add_08":{"width":441,"height":431},"ps_vfx_b_add_09":{"width":441,"height":431},"ps_vfx_b_add_10":{"width":441,"height":431},"ps_vfx_b_add_11":{"width":441,"height":431},"ps_vfx_b_add_12":{"width":441,"height":431},"ps_vfx_b_add_13":{"width":441,"height":431},"ps_vfx_b_add_14":{"width":441,"height":431},"ps_vfx_b_add_15":{"width":441,"height":431},"ps_vfx_b_add_16":{"width":441,"height":431},"ps_vfx_b_add_17":{"width":441,"height":431},"ps_vfx_b_add_18":{"width":441,"height":431},"ps_vfx_b_add_19":{"width":441,"height":431},"ps_vfx_b_add_20":{"width":441,"height":431}},"fg2":{"ps_vfx_c_add_00":{"width":454,"height":456},"ps_vfx_c_add_01":{"width":454,"height":456},"ps_vfx_c_add_02":{"width":454,"height":456},"ps_vfx_c_add_03":{"width":454,"height":456},"ps_vfx_c_add_04":{"width":454,"height":456},"ps_vfx_c_add_05":{"width":454,"height":456},"ps_vfx_c_add_06":{"width":454,"height":456},"ps_vfx_c_add_07":{"width":454,"height":456}}}},"animations":{"animation":{"slots":{"dikuang":{"color":[{"time":0,"color":"ffffff00"},{"time":0.1667,"color":"ffffffff"}]},"dikuang2":{"color":[{"time":0,"color":"ffffff00"},{"time":0.1667,"color":"ffffffff"}]},"dikuang3":{"color":[{"time":0,"color":"ffffff00","curve":"stepped"},{"time":0.1667,"color":"ffffff00"},{"time":0.4333,"color":"ffffffff"},{"time":0.6667,"color":"ffffff00","curve":"stepped"},{"time":1.3333,"color":"ffffff00"},{"time":1.6,"color":"ffffffff"},{"time":1.8333,"color":"ffffff00","curve":"stepped"},{"time":2,"color":"ffffff00"}]},"fg":{"attachment":[{"time":0,"name":"ps_vfx_b_add_00"},{"time":0.0667,"name":"ps_vfx_b_add_01"},{"time":0.1333,"name":"ps_vfx_b_add_02"},{"time":0.2,"name":"ps_vfx_b_add_03"},{"time":0.2667,"name":"ps_vfx_b_add_04"},{"time":0.3333,"name":"ps_vfx_b_add_05"},{"time":0.4,"name":"ps_vfx_b_add_06"},{"time":0.4667,"name":"ps_vfx_b_add_07"},{"time":0.5333,"name":"ps_vfx_b_add_08"},{"time":0.6,"name":"ps_vfx_b_add_09"},{"time":0.6667,"name":"ps_vfx_b_add_10"},{"time":0.7333,"name":"ps_vfx_b_add_11"},{"time":0.8,"name":"ps_vfx_b_add_12"},{"time":0.8667,"name":"ps_vfx_b_add_13"},{"time":0.9333,"name":"ps_vfx_b_add_14"},{"time":1,"name":"ps_vfx_b_add_15"},{"time":1.0667,"name":"ps_vfx_b_add_16"},{"time":1.1333,"name":"ps_vfx_b_add_17"},{"time":1.2,"name":"ps_vfx_b_add_18"},{"time":1.2667,"name":"ps_vfx_b_add_19"},{"time":1.3333,"name":"ps_vfx_b_add_20"},{"time":1.4,"name":null}]},"fg2":{"attachment":[{"time":0,"name":"ps_vfx_c_add_00"},{"time":0.0667,"name":"ps_vfx_c_add_01"},{"time":0.1333,"name":"ps_vfx_c_add_02"},{"time":0.2,"name":"ps_vfx_c_add_03"},{"time":0.2667,"name":"ps_vfx_c_add_04"},{"time":0.3333,"name":"ps_vfx_c_add_05"},{"time":0.4,"name":"ps_vfx_c_add_06"},{"time":0.4667,"name":"ps_vfx_c_add_07"},{"time":0.5333,"name":null}]}},"bones":{"dikuang3":{"scale":[{"time":0,"x":0.5,"y":0.5,"curve":"stepped"},{"time":0.1667,"x":0.5,"y":0.5},{"time":0.6667,"x":0.65,"y":0.65},{"time":1.3333,"x":0.5,"y":0.5},{"time":1.8333,"x":0.65,"y":0.65,"curve":"stepped"},{"time":2,"x":0.65,"y":0.65}]}}}}},[0,1]]],0,0,[0,0],[-1,-2],[0,1]]